raman_fitting/__init__.py
raman_fitting/_version.py
raman_fitting/types.py
raman_fitting/config/__init__.py
raman_fitting/config/base_settings.py
raman_fitting/config/filepath_helper.py
raman_fitting/config/logging_config.py
raman_fitting/config/path_settings.py
raman_fitting/config/default_models/__init__.py
raman_fitting/config/default_models/first_order.toml
raman_fitting/config/default_models/normalization.toml
raman_fitting/config/default_models/second_order.toml
raman_fitting/config/default_models/spectrum_regions.toml
raman_fitting/delegating/__init__.py
raman_fitting/delegating/main_delegator.py
raman_fitting/delegating/models.py
raman_fitting/delegating/pre_processing.py
raman_fitting/delegating/run_fit_multi.py
raman_fitting/delegating/run_fit_spectrum.py
raman_fitting/example_fixtures/Si_spectrum01.txt
raman_fitting/example_fixtures/__init__.py
raman_fitting/example_fixtures/raman_fitting.toml
raman_fitting/example_fixtures/testDW38C_pos1.txt
raman_fitting/example_fixtures/testDW38C_pos2.txt
raman_fitting/example_fixtures/testDW38C_pos3.txt
raman_fitting/example_fixtures/testDW38C_pos4.txt
raman_fitting/exports/__init__.py
raman_fitting/exports/exporter.py
raman_fitting/exports/file_table.py
raman_fitting/exports/plot_formatting.py
raman_fitting/exports/plotting_fit_results.py
raman_fitting/exports/plotting_raw_data.py
raman_fitting/imports/__init__.py
raman_fitting/imports/collector.py
raman_fitting/imports/models.py
raman_fitting/imports/spectrumdata_parser.py
raman_fitting/imports/files/file_finder.py
raman_fitting/imports/files/file_indexer.py
raman_fitting/imports/files/index_funcs.py
raman_fitting/imports/files/index_helpers.py
raman_fitting/imports/files/metadata.py
raman_fitting/imports/files/utils.py
raman_fitting/imports/files/validators.py
raman_fitting/imports/samples/models.py
raman_fitting/imports/samples/sample_id_helpers.py
raman_fitting/imports/spectrum/__init__.py
raman_fitting/imports/spectrum/datafile_parsers.py
raman_fitting-0.8.0.dist-info/METADATA
raman_fitting-0.8.0.dist-info/WHEEL
raman_fitting-0.8.0.dist-info/entry_points.txt
raman_fitting-0.8.0.dist-info/licenses/LICENSE
raman_fitting-0.8.0.dist-info/RECORD
