Metadata-Version: 2.1
Name: raman_fitting
Version: 0.8.0
Summary: Python framework for the batch processing and deconvolution of raman spectra.
Project-URL: homepage, https://pypi.org/project/raman-fitting/
Project-URL: repository, https://github.com/MyPyDavid/raman-fitting.git
Author-email: David Wallace <mypydavid@proton.me>
License: MIT License
License-File: LICENSE
Keywords: Raman,batch processing,carbonaceous materials,deconvolution,fitting,spectroscopy
Classifier: Intended Audience :: Science/Research
Classifier: License :: OSI Approved :: MIT License
Classifier: Natural Language :: English
Classifier: Programming Language :: Python
Classifier: Programming Language :: Python :: 3 :: Only
Classifier: Programming Language :: Python :: 3.11
Classifier: Programming Language :: Python :: Implementation :: CPython
Classifier: Programming Language :: Python :: Implementation :: PyPy
Classifier: Topic :: Scientific/Engineering :: Chemistry
Classifier: Topic :: Scientific/Engineering :: Physics
Requires-Dist: lmfit~=1.2.2
Requires-Dist: loguru>=0.7
Requires-Dist: matplotlib~=3.8.0
Requires-Dist: mpire[dill]~=2.10.0
Requires-Dist: numpy~=1.26.1
Requires-Dist: pandas~=2.1.2
Requires-Dist: pydantic-numpy>=4.1
Requires-Dist: pydantic-settings>=2.1
Requires-Dist: pydantic>=2.5
Requires-Dist: scipy~=1.11.3
Requires-Dist: tablib~=3.5.0
Requires-Dist: typer[all]
Provides-Extra: dev
Requires-Dist: autopep8; extra == 'dev'
Requires-Dist: black; extra == 'dev'
Requires-Dist: bump2version; extra == 'dev'
Requires-Dist: flake8; extra == 'dev'
Requires-Dist: isort; extra == 'dev'
Requires-Dist: pydocstyle; extra == 'dev'
Requires-Dist: pylint; extra == 'dev'
Requires-Dist: raman-fitting[pytest]; extra == 'dev'
Provides-Extra: pytest
Requires-Dist: mock; extra == 'pytest'
Requires-Dist: pytest; extra == 'pytest'
Requires-Dist: pytest-cov; extra == 'pytest'
Requires-Dist: pytest-flake8; extra == 'pytest'
Requires-Dist: wheel; extra == 'pytest'
